structured_output_prompt/__init__.py
structured_output_prompt/model_generator.py
structured_output_prompt/template_manager.py
structured_output_prompt/templates.py
structured_output_prompt-1.0.0.dist-info/licenses/LICENSE
structured_output_prompt-1.0.0.dist-info/METADATA
structured_output_prompt-1.0.0.dist-info/WHEEL
structured_output_prompt-1.0.0.dist-info/top_level.txt
structured_output_prompt-1.0.0.dist-info/RECORD
