Metadata-Version: 2.4
Name: structured-output-prompt
Version: 1.0.0
Summary: 一个Python库，用于从Pydantic模型生成结构化输出提示，专为不支持JSON Schema的大语言模型设计。 / A Python library for generating structured output prompts from Pydantic models, designed for LLMs that do not support JSON Schema.
Author-email: Apauto-to-all <apautotoall@outlook.com>
License-Expression: MIT
Project-URL: Homepage, https://github.com/Apauto-to-all/structured_output_prompt
Requires-Python: >=3.12
License-File: LICENSE
Requires-Dist: pydantic>=2.11.7
Dynamic: license-file
